<?xml version="1.0" encoding="UTF-8"?>
<Configuration status="WARN">
    <Appenders>
        <Console name="Console" target="SYSTEM_OUT">
            <PatternLayout pattern="%d{HH:mm:ss.SSS} [%t] %-5level %logger{36} - %msg%n"/>
        </Console>
        <!--For logging to file:
        <File name="File" fileName="logs/error.log" value="warn">
            <PatternLayout>
                <Pattern>%d %p %c{1.} [%t] %m%n</Pattern>
            </PatternLayout>
        </File>-->
    </Appenders>
    <Loggers>
        <Root level="info"><!-- for debug set to "debug" -->
            <AppenderRef ref="Console"/>
            <!--For logging to file: <AppenderRef ref="File"/>-->
        </Root>
    </Loggers>
</Configuration>